yaml_checker/__init__.py
yaml_checker/schema.py
yaml_checker/validator.py
yaml_checker-0.1.dist-info/LICENSE.txt
yaml_checker-0.1.dist-info/METADATA
yaml_checker-0.1.dist-info/WHEEL
yaml_checker-0.1.dist-info/top_level.txt
yaml_checker-0.1.dist-info/RECORD
