Metadata-Version: 2.1
Name: yaml-checker
Version: 0.1
Summary: Check the YAML schema and content range
Home-page: https://gitlab.com/itops6/cloud-team/iac-projects/yaml-checker
Author: Abhinav Chadha
Author-email: abhinav.chadha@techspirit.co
License: MIT
Keywords: yaml,checker,validator
Platform: UNKNOWN
Classifier: Development Status :: 3 - Alpha
Classifier: Intended Audience :: Developers
Classifier: Topic :: Software Development :: Build Tools
Classifier: License :: OSI Approved :: MIT License
Classifier: Programming Language :: Python :: 3
Classifier: Programming Language :: Python :: 3.4
Classifier: Programming Language :: Python :: 3.5
Classifier: Programming Language :: Python :: 3.6
Requires-Dist: cerberus
Requires-Dist: pyyaml
